pynanomapper/__init__.py
pynanomapper/aa.py
pynanomapper/annotation.py
pynanomapper/client_ambit.py
pynanomapper/client_solr.py
pynanomapper/clients/__init__.py
pynanomapper/clients/authservice.py
pynanomapper/clients/datamodel_simple.py
pynanomapper/clients/h5converter.py
pynanomapper/clients/h5service.py
pynanomapper/clients/service_charisma.py
pynanomapper/clients/service_import.py
pynanomapper/datamodel/__init__.py
pynanomapper/datamodel/nexus_image.py
pynanomapper/datamodel/templates/__init__.py
pynanomapper/datamodel/templates/blueprint.py
pynanomapper/datamodel/templates/template_designer.py
pynanomapper/resource/__init__.py
pynanomapper/resource/nmparser/DEFAULT_TABLE.json
pynanomapper/resource/nmparser/__init__.py
pynanomapper/resource/nmparser/platelayout_384well.xlsx
pynanomapper/resource/nmparser/platelayout_96well.xlsx
pynanomapper/resource/nmparser/template_pchem.xlsx
pynanomapper/units.py
pynanomapper-2.1.0.dist-info/LICENSE
pynanomapper-2.1.0.dist-info/METADATA
pynanomapper-2.1.0.dist-info/WHEEL
pynanomapper-2.1.0.dist-info/RECORD
